impl/consistent_hashing.py
py_consistent_hash-1.0.1.dist-info/LICENSE
py_consistent_hash-1.0.1.dist-info/METADATA
py_consistent_hash-1.0.1.dist-info/WHEEL
py_consistent_hash-1.0.1.dist-info/top_level.txt
py_consistent_hash-1.0.1.dist-info/RECORD
