Metadata-Version: 2.1
Name: py-consistent-hash
Version: 1.0.1
Summary: A consistent hash implementation in python
Author-email: Gaurav Tiwari <gtinside@gmail.com>
License: MIT License
Project-URL: Homepage, https://github.com/gtinside/consistent-hashing
Keywords: hash,consistent hash
Classifier: License :: OSI Approved :: MIT License
Classifier: Programming Language :: Python
Classifier: Programming Language :: Python :: 3
Requires-Python: >=3.9
License-File: LICENSE
